{
  "language": "en",
  "updated_at": "2026-06-29T13:14+00:00",
  "count": 24,
  "latest": [
    {
      "category": "World / news",
      "title": "Mideast Live Updates: U.S. and Iran Set for New Talks in Qatar, Trump Says",
      "summary": "President Trump said the discussions would take place on Tuesday, after the United States and Iran exchanged strikes over the weekend. Iran did not…",
      "source": "The New York Times",
      "link": "https://www.nytimes.com/live/2026/06/29/world/hormuz-us-iran-strikes",
      "image": "https://static01.nyt.com/images/2026/06/29/multimedia/29mideast-live-header-zwqg/29mideast-live-header-zwqg-mediumSquareAt3X.jpg",
      "time": "today"
    },
    {
      "category": "Business / markets",
      "title": "Comcast soars 20% after announcing it will spin off NBCUniversal and Sky from cable business",
      "summary": "Comcast said it will separate into two publicly traded companies through a tax-free spinoff of NBCUniversal and Sky.",
      "source": "CNBC",
      "link": "https://www.cnbc.com/2026/06/29/comcast-announces-it-will-spin-off-media-and-tech-wings-into-separate-public-companies.html",
      "image": "https://image.cnbcfm.com/api/v1/image/108291902-1776271938523-gettyimages-2257538298-img_6716.jpeg?v=1776271965&w=1920&h=1080",
      "time": "today"
    },
    {
      "category": "Technology",
      "title": "The Flipper Zero creators’ Busy Bar productivity display will go on sale next month",
      "summary": "First announced over a year ago in April 2025, the Busy Bar will be available for purchase starting on July 14th when the device also starts…",
      "source": "The Verge",
      "link": "https://www.theverge.com/tech/957784/flipper-devices-busy-bar-productivity-multitool-timer-led-display-presale",
      "image": "https://platform.theverge.com/wp-content/uploads/sites/2/2026/06/busybar1.jpg?quality=90&strip=all&crop=0%2C10.723165084465%2C100%2C78.55366983107&w=1200",
      "time": "today"
    },
    {
      "category": "Science",
      "title": "Compliant farmers could face fewer inspections under new water pollution proposals",
      "summary": "The latest draft Nutrients Action Policy caused controversy when it was initially launched last year.",
      "source": "BBC",
      "link": "https://www.bbc.co.uk/news/articles/cewq8jvekqgo?at_medium=RSS&at_campaign=rss",
      "image": "https://ichef.bbci.co.uk/ace/standard/240/cpsprodpb/10f3/live/024e1a20-73af-11f1-9da1-db101e3ae6ed.jpg",
      "time": "today"
    }
  ],
  "radar": [
    {
      "category": "World / news",
      "title": "Venezuela earthquake aftershock hits capital city as ‘miracle’ rescues reported – latest…",
      "summary": "No damage reported in 4.6 magnitude aftershock; At least 1,450 people are known to have died in initial quakes but number is expected to rise In an…",
      "source": "The Guardian",
      "link": "https://www.theguardian.com/world/live/2026/jun/29/venezuela-earthquakes-search-rescue-latest-updates",
      "image": "https://i.guim.co.uk/img/media/97379d7dfd7bcdec7f780a6631ae2315b1c9c1e3/520_0_6338_5070/master/6338.jpg?width=140&quality=85&auto=format&fit=max&s=69e4763c1f473e062a45aee42c694d3e",
      "time": "today"
    },
    {
      "category": "Business / markets",
      "title": "Inspired by Wimbledon and the World Cup? Here's how to play sport for free",
      "summary": "As the world's best players begin play at Wimbledon, how can you get into sport on a budget.",
      "source": "BBC",
      "link": "https://www.bbc.co.uk/news/articles/crlw2xw1yy2o?at_medium=RSS&at_campaign=rss",
      "image": "https://ichef.bbci.co.uk/ace/standard/240/cpsprodpb/fbb2/live/cc51f620-714d-11f1-8836-a15622d321c0.png",
      "time": "today"
    },
    {
      "category": "Technology",
      "title": "The Busy Bar Is a Gadget to Get People to Leave You Alone",
      "summary": "Flipper Devices, a company that built a banned hacking device, now wants to hack your attention span.",
      "source": "WIRED",
      "link": "https://www.wired.com/story/busy-bar-is-a-gadget-to-get-people-to-leave-you-alone/",
      "image": "https://media.wired.com/photos/6a3e755d5cdc2b309c97a471/master/pass/BSB%20M1%20Shop%20Nov25%20mounted%20screen%20v1%20251117%2001%20(1)%20copy.jpg",
      "time": "today"
    },
    {
      "category": "Business / markets",
      "title": "British American Tobacco to cut 9,000 jobs",
      "summary": "The company had said earlier this year it was planning savings to make it \"more digital and AI-focused\".",
      "source": "BBC",
      "link": "https://www.bbc.co.uk/news/articles/c3vyen243dno?at_medium=RSS&at_campaign=rss",
      "image": "https://ichef.bbci.co.uk/ace/standard/240/cpsprodpb/2a28/live/96128100-73a1-11f1-8e1d-bbbb1017d210.jpg",
      "time": "today"
    }
  ]
}