{
  "updated_at": "2026-07-14T17:52:10+02:00",
  "prices": {
    "eurusd": {
      "price": 1.1431183815002441,
      "timestamp": "2026-07-14T17:52:02+02:00",
      "current_price_updated_at": "2026-07-14T17:52:02+02:00",
      "source": "Yahoo Finance:EURUSD=X:chart:1d:1m",
      "fresh": true,
      "note": ""
    },
    "sp500_futures": {
      "price": 7580.5,
      "timestamp": "2026-07-14T17:42:09+02:00",
      "current_price_updated_at": "2026-07-14T17:42:09+02:00",
      "source": "Yahoo Finance:ES=F:chart:1d:1m",
      "fresh": true,
      "note": ""
    },
    "btcusd": {
      "price": 64620.80078125,
      "timestamp": "2026-07-14T17:52:05+02:00",
      "current_price_updated_at": "2026-07-14T17:52:05+02:00",
      "source": "Yahoo Finance:BTC-USD:chart:1d:1m",
      "fresh": true,
      "note": ""
    }
  }
}
