{
  "updated_at": "2026-07-23T09:20:31+02:00",
  "prices": {
    "eurusd": {
      "price": 1.142987847328186,
      "timestamp": "2026-07-23T09:20:20+02:00",
      "current_price_updated_at": "2026-07-23T09:20:20+02:00",
      "source": "Yahoo Finance:EURUSD=X:chart:1d:1m",
      "fresh": true,
      "note": ""
    },
    "sp500_futures": {
      "price": 7507.5,
      "timestamp": "2026-07-23T09:10:30+02:00",
      "current_price_updated_at": "2026-07-23T09:10:30+02:00",
      "source": "Yahoo Finance:ES=F:chart:1d:1m",
      "fresh": true,
      "note": ""
    },
    "btcusd": {
      "price": 65364.01953125,
      "timestamp": "2026-07-23T09:20:26+02:00",
      "current_price_updated_at": "2026-07-23T09:20:26+02:00",
      "source": "Yahoo Finance:BTC-USD:chart:1d:1m",
      "fresh": true,
      "note": ""
    }
  }
}
