{
  "updated_at": "2026-06-19T22:05:58+02:00",
  "prices": {
    "eurusd": {
      "price": 1.1482374668121338,
      "timestamp": "2026-06-19T22:05:52+02:00",
      "current_price_updated_at": "2026-06-19T22:05:52+02:00",
      "source": "Yahoo Finance:EURUSD=X:chart:1d:1m",
      "fresh": true,
      "note": ""
    },
    "sp500_futures": {
      "price": 7536.75,
      "timestamp": "2026-06-19T05:58:00+02:00",
      "current_price_updated_at": "2026-06-19T05:58:00+02:00",
      "source": "Yahoo Finance:ES=F:chart:1d:1m",
      "fresh": true,
      "note": ""
    }
  }
}
